{
  "id": "221",
  "number": 221,
  "title": "Que mi mente esté en paz y que todos mis pensamientos se aquieten.",
  "originalText": "1. Padre, hoy vengo a Ti en busca de la paz que sólo Tú puedes dar. 2 Vengo en silencio. 3 Y en la quietud de mi corazón -en lo más recóndito de mi mente- , espero y estoy a la escucha de Tu Voz. 4 Padre mío, háblame hoy. 5 Vengo a oír Tu Voz en silencio, con certeza y con amor, seguro de que oirás mi llamada y de que me responderás.\n\n2. Y ahora aguardamos silenciosamente. 2 Dios está aquí porque esperamos juntos. 3 Estoy seguro de que Él te hablará y de que tú le oirás. 4 Acepta mi confianza, pues es la tuya. 5 Nuestras mentes están unidas. 6 Esperamos con un solo propósito: oír la respuesta de nuestro Padre a nuestra llamada, dejar que nuestros pensamientos se aquieten y encontrar Su paz, para oírle hablar de lo que nosotros somos y para que Él Se revele a Su Hijo.",
  "originalTextLoaded": true,
  "sourceUrl": "https://aprendiendouncursodemilagros.blogspot.com/2017/08/ucdm-libro-de-ejercicios-leccion-221.html",
  "commentary": {
    "teachingExplanation": "",
    "purpose": "",
    "practicalInstructions": [],
    "psychological": "",
    "spiritual": "",
    "courseRelation": "",
    "practiceTips": [],
    "conclusion": "",
    "dailyExamples": [],
    "guideExample": {
      "title": "",
      "situation": "",
      "shift": ""
    },
    "finalReflection": "",
    "glossary": []
  },
  "commentaryReady": false,
  "video": {
    "type": "none",
    "url": "",
    "status": "soon"
  },
  "commonImageUrl": null,
  "createdAt": 1781976638250,
  "updatedAt": 1781976638250
}